LICENSE
MANIFEST.in
README.md
setup.py
django_shibboleth_eds.egg-info/PKG-INFO
django_shibboleth_eds.egg-info/SOURCES.txt
django_shibboleth_eds.egg-info/dependency_links.txt
django_shibboleth_eds.egg-info/top_level.txt
shibboleth_eds/__init__.py
shibboleth_eds/urls.py
shibboleth_eds/views.py
shibboleth_eds/static/shibboleth_eds/blank.gif
shibboleth_eds/static/shibboleth_eds/idpselect.css
shibboleth_eds/static/shibboleth_eds/idpselect.js
shibboleth_eds/templates/shibboleth_eds/discovery.html
shibboleth_eds/templates/shibboleth_eds/idpselect_config.js