Metadata-Version: 1.1
Name: django-shibboleth-eds
Version: 0.6.1
Summary: Django app to embed Shibboleth Embedded Discovery Service into your Django project.
Home-page: https://github.com/hu-berlin-cms/django-shibboleth-eds
Author: Enno Gröper
Author-email: enno.groeper@cms.hu-berlin.de
License: Apache 2.0
Platform: UNKNOWN
Classifier: Environment :: Web Environment
Classifier: Framework :: Django
Classifier: Framework :: Django :: 1.8
Classifier: Intended Audience :: Developers
Classifier: License :: OSI Approved :: Apache Software License
Classifier: Operating System :: OS Independent
Classifier: Programming Language :: Python
Classifier: Programming Language :: Python :: 2
Classifier: Programming Language :: Python :: 3
Classifier: Programming Language :: Python :: 3.4
Classifier: Programming Language :: Python :: 3.5
Classifier: Topic :: Internet :: WWW/HTTP
Classifier: Topic :: Internet :: WWW/HTTP :: Dynamic Content
